bk_rm_no_stock/__init__.py
bk_rm_no_stock/bk_main.py
bk_rm_no_stock-0.0.2.dist-info/METADATA
bk_rm_no_stock-0.0.2.dist-info/WHEEL
bk_rm_no_stock-0.0.2.dist-info/entry_points.txt
bk_rm_no_stock-0.0.2.dist-info/top_level.txt
bk_rm_no_stock-0.0.2.dist-info/RECORD
